{"generatedAt":"2026-07-24T13:18:53.024006+09:00","windowHours":24,"keywords":[{"keyword":"화재","count":109,"prevDailyAvg":13.0,"score":96.0,"sampleArticleIds":["8f6733e0eb5a","4cca4f7f17ef","ccf015d1d827"]},{"keyword":"쿠팡","count":113,"prevDailyAvg":21.7,"score":91.3,"sampleArticleIds":["8f6733e0eb5a","4cca4f7f17ef","ccf015d1d827"]},{"keyword":"동아제약","count":88,"prevDailyAvg":0.0,"score":88.0,"sampleArticleIds":["eb75b58867ed","96d8362e1133","8037140023bd"]},{"keyword":"동아쏘시오홀딩스","count":78,"prevDailyAvg":0.0,"score":78.0,"sampleArticleIds":["eb75b58867ed","8037140023bd","ee8d56259179"]},{"keyword":"농심","count":54,"prevDailyAvg":0.0,"score":54.0,"sampleArticleIds":["c0baa6c243a4","67bbd0ea54a1","14c89c58b3bc"]},{"keyword":"인천","count":61,"prevDailyAvg":8.3,"score":52.7,"sampleArticleIds":["ccf015d1d827","0c5739334e1f","242e596d617a"]},{"keyword":"흡수합병","count":52,"prevDailyAvg":0.0,"score":52.0,"sampleArticleIds":["8037140023bd","f7bab4ee27f2","a075413fd3b2"]},{"keyword":"주민","count":47,"prevDailyAvg":0.0,"score":47.0,"sampleArticleIds":["8f6733e0eb5a","4cca4f7f17ef","ccf015d1d827"]},{"keyword":"AI","count":81,"prevDailyAvg":36.3,"score":44.7,"sampleArticleIds":["8dc32a7ad058","32dae6602b25","c1136094caa5"]},{"keyword":"물류센터","count":52,"prevDailyAvg":7.3,"score":44.7,"sampleArticleIds":["242e596d617a","e9845a07f0b0","7e43840fc62f"]},{"keyword":"피해","count":44,"prevDailyAvg":0.7,"score":43.3,"sampleArticleIds":["8f6733e0eb5a","4cca4f7f17ef","ccf015d1d827"]},{"keyword":"가격","count":46,"prevDailyAvg":4.3,"score":41.7,"sampleArticleIds":["c0baa6c243a4","de351a63395c","a4a17ca9b2be"]},{"keyword":"인상","count":42,"prevDailyAvg":1.3,"score":40.7,"sampleArticleIds":["eccca8c180be","c0baa6c243a4","67bbd0ea54a1"]},{"keyword":"국내","count":38,"prevDailyAvg":3.7,"score":34.3,"sampleArticleIds":["27e3a2fd1dc1","9bd9389181cf","bdd9beaa78dc"]},{"keyword":"라이브","count":42,"prevDailyAvg":8.0,"score":34.0,"sampleArticleIds":["26f21976b518","1bf71290f6f6","6ecde2fc7eca"]},{"keyword":"브랜드","count":41,"prevDailyAvg":10.7,"score":30.3,"sampleArticleIds":["dc733c3077f9","5a937e2586da","1934e9f24d7b"]},{"keyword":"GS25","count":33,"prevDailyAvg":3.7,"score":29.3,"sampleArticleIds":["d9d3930091d1","7cbd4e58921d","4227c531d225"]},{"keyword":"전환","count":29,"prevDailyAvg":2.0,"score":27.0,"sampleArticleIds":["f7bab4ee27f2","3219f6d26a79","7b5239768e08"]},{"keyword":"글로벌","count":30,"prevDailyAvg":3.7,"score":26.3,"sampleArticleIds":["10a9da7c78c0","8037140023bd","b2d2e9b324d8"]},{"keyword":"메디큐브","count":25,"prevDailyAvg":0.0,"score":25.0,"sampleArticleIds":["bdd9beaa78dc","f9d6e9cfd165","c025998e9d6d"]}]}
